rasterfairy/__init__.py
rasterfairy/coonswarp.py
rasterfairy/prime.py
rasterfairy/rasterfairy.py
rasterfairy/rfoptimizer.py
rasterfairy/utils.py
rasterfairy_py3-1.0.5.dist-info/LICENSE
rasterfairy_py3-1.0.5.dist-info/METADATA
rasterfairy_py3-1.0.5.dist-info/WHEEL
rasterfairy_py3-1.0.5.dist-info/top_level.txt
rasterfairy_py3-1.0.5.dist-info/RECORD
